LICENSE
NOTICE
apache_iggy-0.6.0.dist-info/METADATA
apache_iggy-0.6.0.dist-info/WHEEL
apache_iggy-0.6.0.dist-info/licenses/LICENSE
apache_iggy-0.6.0.dist-info/licenses/NOTICE
apache_iggy/__init__.py
apache_iggy/__init__.pyi
apache_iggy/apache_iggy.cpython-312-x86_64-linux-gnu.so
apache_iggy/py.typed
apache_iggy-0.6.0.dist-info/RECORD
